sqlalchemy_rope/__about__.py
sqlalchemy_rope/__init__.py
sqlalchemy_rope/session.py
SQLAlchemy_Rope-0.1.0.dist-info/LICENSE
SQLAlchemy_Rope-0.1.0.dist-info/METADATA
SQLAlchemy_Rope-0.1.0.dist-info/WHEEL
SQLAlchemy_Rope-0.1.0.dist-info/top_level.txt
SQLAlchemy_Rope-0.1.0.dist-info/RECORD
